odoo10_addon_donation_direct_debit-10.0.1.0.0.99.dev9-py2.7-nspkg.pth
odoo/addons/donation_direct_debit/README.rst
odoo/addons/donation_direct_debit/__init__.py
odoo/addons/donation_direct_debit/__manifest__.py
odoo/addons/donation_direct_debit/donation.py
odoo/addons/donation_direct_debit/donation_demo.xml
odoo/addons/donation_direct_debit/donation_view.xml
odoo/addons/donation_direct_debit/i18n/de.po
odoo/addons/donation_direct_debit/i18n/donation_direct_debit.pot
odoo/addons/donation_direct_debit/i18n/fr.po
odoo/addons/donation_direct_debit/security/ir.model.access.csv
odoo/addons/donation_direct_debit/static/description/icon.png
odoo/addons/donation_direct_debit/tests/__init__.py
odoo/addons/donation_direct_debit/tests/test_direct_debit.py
odoo10_addon_donation_direct_debit-10.0.1.0.0.99.dev9.dist-info/METADATA
odoo10_addon_donation_direct_debit-10.0.1.0.0.99.dev9.dist-info/RECORD
odoo10_addon_donation_direct_debit-10.0.1.0.0.99.dev9.dist-info/WHEEL
odoo10_addon_donation_direct_debit-10.0.1.0.0.99.dev9.dist-info/namespace_packages.txt
odoo10_addon_donation_direct_debit-10.0.1.0.0.99.dev9.dist-info/top_level.txt
